<annotation>
	<folder></folder>
	<filename>26_jpg.rf.57d2b340ea7e6939035b3f5399fb52ad.jpg</filename>
	<path>26_jpg.rf.57d2b340ea7e6939035b3f5399fb52ad.jpg</path>
	<source>
		<database>roboflow.com</database>
	</source>
	<size>
		<width>640</width>
		<height>640</height>
		<depth>3</depth>
	</size>
	<segmented>0</segmented>
	<object>
		<name>dent</name>
		<pose>Unspecified</pose>
		<truncated>0</truncated>
		<difficult>0</difficult>
		<occluded>0</occluded>
		<bndbox>
			<xmin>236</xmin>
			<xmax>450</xmax>
			<ymin>291</ymin>
			<ymax>484</ymax>
		</bndbox>
	</object>
	<object>
		<name>dent</name>
		<pose>Unspecified</pose>
		<truncated>0</truncated>
		<difficult>0</difficult>
		<occluded>0</occluded>
		<bndbox>
			<xmin>487</xmin>
			<xmax>571</xmax>
			<ymin>191</ymin>
			<ymax>392</ymax>
		</bndbox>
	</object>
</annotation>
