<annotation>
	<folder></folder>
	<filename>efc4aa1a-DSCF6973_JPG_jpg.rf.a46e04b536d30e4e554a1c45fe544ef8.jpg</filename>
	<path>efc4aa1a-DSCF6973_JPG_jpg.rf.a46e04b536d30e4e554a1c45fe544ef8.jpg</path>
	<source>
		<database>roboflow.com</database>
	</source>
	<size>
		<width>640</width>
		<height>640</height>
		<depth>3</depth>
	</size>
	<segmented>0</segmented>
	<object>
		<name>rust</name>
		<pose>Unspecified</pose>
		<truncated>0</truncated>
		<difficult>0</difficult>
		<occluded>0</occluded>
		<bndbox>
			<xmin>388</xmin>
			<xmax>538</xmax>
			<ymin>243</ymin>
			<ymax>641</ymax>
		</bndbox>
	</object>
	<object>
		<name>rust</name>
		<pose>Unspecified</pose>
		<truncated>0</truncated>
		<difficult>0</difficult>
		<occluded>0</occluded>
		<bndbox>
			<xmin>308</xmin>
			<xmax>359</xmax>
			<ymin>569</ymin>
			<ymax>622</ymax>
		</bndbox>
	</object>
	<object>
		<name>rust</name>
		<pose>Unspecified</pose>
		<truncated>0</truncated>
		<difficult>0</difficult>
		<occluded>0</occluded>
		<bndbox>
			<xmin>229</xmin>
			<xmax>262</xmax>
			<ymin>512</ymin>
			<ymax>561</ymax>
		</bndbox>
	</object>
	<object>
		<name>rust</name>
		<pose>Unspecified</pose>
		<truncated>0</truncated>
		<difficult>0</difficult>
		<occluded>0</occluded>
		<bndbox>
			<xmin>286</xmin>
			<xmax>313</xmax>
			<ymin>243</ymin>
			<ymax>281</ymax>
		</bndbox>
	</object>
	<object>
		<name>rust</name>
		<pose>Unspecified</pose>
		<truncated>0</truncated>
		<difficult>0</difficult>
		<occluded>0</occluded>
		<bndbox>
			<xmin>451</xmin>
			<xmax>476</xmax>
			<ymin>206</ymin>
			<ymax>272</ymax>
		</bndbox>
	</object>
	<object>
		<name>rust</name>
		<pose>Unspecified</pose>
		<truncated>0</truncated>
		<difficult>0</difficult>
		<occluded>0</occluded>
		<bndbox>
			<xmin>477</xmin>
			<xmax>506</xmax>
			<ymin>178</ymin>
			<ymax>223</ymax>
		</bndbox>
	</object>
</annotation>
