<annotation>
	<folder></folder>
	<filename>SEGU4243815-6-_JPG.rf.8b6afcd4cb140f3468ed5c1f533baaa9.jpg</filename>
	<path>SEGU4243815-6-_JPG.rf.8b6afcd4cb140f3468ed5c1f533baaa9.jpg</path>
	<source>
		<database>roboflow.com</database>
	</source>
	<size>
		<width>640</width>
		<height>640</height>
		<depth>3</depth>
	</size>
	<segmented>0</segmented>
	<object>
		<name>dent</name>
		<pose>Unspecified</pose>
		<truncated>0</truncated>
		<difficult>0</difficult>
		<occluded>0</occluded>
		<bndbox>
			<xmin>602</xmin>
			<xmax>641</xmax>
			<ymin>186</ymin>
			<ymax>293</ymax>
		</bndbox>
	</object>
	<object>
		<name>dent</name>
		<pose>Unspecified</pose>
		<truncated>0</truncated>
		<difficult>0</difficult>
		<occluded>0</occluded>
		<bndbox>
			<xmin>180</xmin>
			<xmax>338</xmax>
			<ymin>30</ymin>
			<ymax>519</ymax>
		</bndbox>
	</object>
	<object>
		<name>dent</name>
		<pose>Unspecified</pose>
		<truncated>0</truncated>
		<difficult>0</difficult>
		<occluded>0</occluded>
		<bndbox>
			<xmin>565</xmin>
			<xmax>641</xmax>
			<ymin>63</ymin>
			<ymax>129</ymax>
		</bndbox>
	</object>
</annotation>
