<annotation>
	<folder></folder>
	<filename>TCNU5825735-4-_JPG_jpg.rf.22a424916611b81d2afdd553f75b9923.jpg</filename>
	<path>TCNU5825735-4-_JPG_jpg.rf.22a424916611b81d2afdd553f75b9923.jpg</path>
	<source>
		<database>roboflow.com</database>
	</source>
	<size>
		<width>640</width>
		<height>640</height>
		<depth>3</depth>
	</size>
	<segmented>0</segmented>
	<object>
		<name>dent</name>
		<pose>Unspecified</pose>
		<truncated>0</truncated>
		<difficult>0</difficult>
		<occluded>0</occluded>
		<bndbox>
			<xmin>77</xmin>
			<xmax>629</xmax>
			<ymin>91</ymin>
			<ymax>543</ymax>
		</bndbox>
	</object>
</annotation>
